MANIFEST.in
setup.py
ate_test_app/LICENSE.txt
ate_test_app/README.md
ate_test_app/__init__.py
ate_test_app/thetest_application.py
ate_test_app/thetestzip_mock.py
ate_test_app/actuators/__init__.py
ate_test_app/actuators/Acceleration/Acceleration.py
ate_test_app/actuators/Acceleration/__init__.py
ate_test_app/actuators/Light/Light.py
ate_test_app/actuators/Light/__init__.py
ate_test_app/actuators/Magnetic_Field/Magnetic_Field.py
ate_test_app/actuators/Magnetic_Field/__init__.py
ate_test_app/actuators/Position/Position.py
ate_test_app/actuators/Position/__init__.py
ate_test_app/actuators/Pressure/Pressure.py
ate_test_app/actuators/Pressure/__init__.py
ate_test_app/actuators/Temperature/Temperature.py
ate_test_app/actuators/Temperature/__init__.py
ate_test_app/auto_script/AutoScriptBase.py
ate_test_app/auto_script/__init__.py
ate_test_app/parameters/LocalResolver.py
ate_test_app/parameters/RemoteResolver.py
ate_test_app/parameters/ResolverBase.py
ate_test_app/parameters/ResolverFactory.py
ate_test_app/parameters/ResolverFactroy.py
ate_test_app/parameters/__init__.py
ate_test_app/sequencers/CommandLineParser.py
ate_test_app/sequencers/ExecutionPolicy.py
ate_test_app/sequencers/Harness.py
ate_test_app/sequencers/MqttClient.py
ate_test_app/sequencers/Sequencer.py
ate_test_app/sequencers/SequencerBase.py
ate_test_app/sequencers/TheTestAppMachine.py
ate_test_app/sequencers/TheTestAppStatusAlive.py
ate_test_app/sequencers/TopicFactory.py
ate_test_app/sequencers/__init__.py
ate_test_app/sequencers/constants.py
ate_test_app/sequencers/DutTesting/DutTestCaseABC.py
ate_test_app/sequencers/DutTesting/Result.py
ate_test_app/sequencers/DutTesting/TestParameters.py
ate_test_app/sequencers/DutTesting/__init__.py
ate_test_app/sequencers/actuators/__init__.py
ate_test_app/sequencers/actuators/generic.py
ate_test_app/sequencers/actuators/temperature/ThermostreamProxy.py
ate_test_app/sequencers/actuators/temperature/__init__.py
ate_test_app/sequencers/binning/BinStrategy.py
semi_ate_test_app.egg-info/PKG-INFO
semi_ate_test_app.egg-info/SOURCES.txt
semi_ate_test_app.egg-info/dependency_links.txt
semi_ate_test_app.egg-info/requires.txt
semi_ate_test_app.egg-info/top_level.txt